financial_advisor_mcp/__init__.py
financial_advisor_mcp/data_provider.py
financial_advisor_mcp/munger_persona.py
financial_advisor_mcp/server.py
financial_advisor_mcp/web_api.py
financial_advisor_munger-0.2.1.dist-info/METADATA
financial_advisor_munger-0.2.1.dist-info/WHEEL
financial_advisor_munger-0.2.1.dist-info/entry_points.txt
financial_advisor_munger-0.2.1.dist-info/RECORD
