Metadata-Version: 2.4
Name: financial-advisor-munger
Version: 0.2.1
Summary: Charlie Munger AI for Investment Analysis - MCP Server and Web API
Project-URL: Homepage, https://github.com/arnaldo-delisio/financial-advisor
Project-URL: Documentation, https://github.com/arnaldo-delisio/financial-advisor/tree/main/financial-advisor-mcp#readme
Project-URL: Repository, https://github.com/arnaldo-delisio/financial-advisor.git
Project-URL: Issues, https://github.com/arnaldo-delisio/financial-advisor/issues
Author-email: Financial Advisor Project <contact@example.com>
License: MIT
Keywords: ai,analysis,charlie-munger,finance,investment,mcp
Classifier: Development Status :: 4 - Beta
Classifier: Intended Audience :: Developers
Classifier: Intended Audience :: Financial and Insurance Industry
Classifier: License :: OSI Approved :: MIT License
Classifier: Programming Language :: Python :: 3
Classifier: Programming Language :: Python :: 3.10
Classifier: Programming Language :: Python :: 3.11
Classifier: Programming Language :: Python :: 3.12
Classifier: Topic :: Office/Business :: Financial :: Investment
Classifier: Topic :: Scientific/Engineering :: Artificial Intelligence
Requires-Python: >=3.10
Requires-Dist: mcp>=0.9.0
Requires-Dist: pandas>=2.3.0
Requires-Dist: pydantic>=2.0.0
Requires-Dist: python-dotenv>=1.1.0
Requires-Dist: requests>=2.31.0
Requires-Dist: yfinance>=0.2.66
Provides-Extra: dev
Requires-Dist: black>=23.0.0; extra == 'dev'
Requires-Dist: build>=1.0.0; extra == 'dev'
Requires-Dist: pytest>=7.0.0; extra == 'dev'
Requires-Dist: ruff>=0.1.0; extra == 'dev'
Requires-Dist: twine>=4.0.0; extra == 'dev'
Provides-Extra: web
Requires-Dist: fastapi>=0.104.0; extra == 'web'
Requires-Dist: python-multipart>=0.0.6; extra == 'web'
Requires-Dist: uvicorn>=0.24.0; extra == 'web'
